proxmox_cli/__init__.py
proxmox_cli/cli.py
proxmox_cli/client.py
proxmox_cli/config.py
proxmox_cli/commands/__init__.py
proxmox_cli/commands/acl.py
proxmox_cli/commands/backup.py
proxmox_cli/commands/container.py
proxmox_cli/commands/group.py
proxmox_cli/commands/helpers.py
proxmox_cli/commands/image.py
proxmox_cli/commands/node.py
proxmox_cli/commands/pool.py
proxmox_cli/commands/role.py
proxmox_cli/commands/storage.py
proxmox_cli/commands/token.py
proxmox_cli/commands/user.py
proxmox_cli/commands/vm.py
proxmox_cli/utils/__init__.py
proxmox_cli/utils/helpers.py
proxmox_cli/utils/output.py
proxmox_cli-0.4.2.dist-info/licenses/LICENSE
proxmox_cli-0.4.2.dist-info/METADATA
proxmox_cli-0.4.2.dist-info/WHEEL
proxmox_cli-0.4.2.dist-info/entry_points.txt
proxmox_cli-0.4.2.dist-info/top_level.txt
proxmox_cli-0.4.2.dist-info/RECORD
