Metadata-Version: 2.4
Name: proxmox-cli
Version: 0.4.2
Summary: A command-line interface for Proxmox Virtual Environment
Home-page: https://github.com/rwgb/proxmox.cli
Author: Ralph Brynard
Author-email: Ralph Brynard <ralph@thebrynards.me>
License: MIT
Project-URL: Homepage, https://github.com/rwgb/proxmox.cli
Project-URL: Documentation, https://github.com/rwgb/proxmox.cli/blob/main/README.md
Project-URL: Repository, https://github.com/rwgb/proxmox.cli
Project-URL: Bug Tracker, https://github.com/rwgb/proxmox.cli/issues
Keywords: proxmox,cli,virtualization,api,management
Classifier: Development Status :: 3 - Alpha
Classifier: Intended Audience :: Developers
Classifier: Intended Audience :: System Administrators
Classifier: License :: OSI Approved :: MIT License
Classifier: Programming Language :: Python :: 3
Classifier: Programming Language :: Python :: 3.8
Classifier: Programming Language :: Python :: 3.9
Classifier: Programming Language :: Python :: 3.10
Classifier: Programming Language :: Python :: 3.11
Classifier: Programming Language :: Python :: 3.12
Classifier: Topic :: System :: Systems Administration
Classifier: Topic :: Utilities
Requires-Python: >=3.8
License-File: LICENSE
Requires-Dist: click>=8.0.0
Requires-Dist: proxmoxer>=2.0.0
Requires-Dist: requests>=2.28.0
Requires-Dist: pyyaml>=6.0
Requires-Dist: rich>=13.0.0
Requires-Dist: tabulate>=0.9.0
Provides-Extra: dev
Requires-Dist: pytest>=7.0.0; extra == "dev"
Requires-Dist: pytest-cov>=4.0.0; extra == "dev"
Requires-Dist: black>=22.0.0; extra == "dev"
Requires-Dist: flake8>=5.0.0; extra == "dev"
Requires-Dist: mypy>=0.990; extra == "dev"
Requires-Dist: isort>=5.11.0; extra == "dev"
Requires-Dist: bump-my-version>=0.15.0; extra == "dev"
Requires-Dist: build>=0.10.0; extra == "dev"
Requires-Dist: twine>=4.0.0; extra == "dev"
Dynamic: author
Dynamic: home-page
Dynamic: license-file
Dynamic: requires-python
